{
  "data.questions": [
    {
      "id": 0,
      "theme.id": 1,
      "source.literal": "As-tu besoin d'aller aux toilettes?",
      "source.variants": [
        "As-tu besoin d'aller aux toilettes?",
        "Tu as besoin d'aller aux toilettes?",
        "T'as besoin d'aller aux toilettes?",
        "Est-ce que tu as besoin d'aller aux toilettes?",
        "Avez-vous besoin d'aller aux toilettes?",
        "Vous avez besoin d'aller aux toilettes?",
        "Est-ce que vous avez besoin d'aller aux toilettes?",
        "Dois-tu aller aux toilettes?",
        "Tu dois aller aux toilettes?"
      ]
    },
    {
      "id": 1,
      "theme.id": 0,
      "source.literal": "As-tu un probl\u00e8me avec un camarade?",
      "source.variants": [
        "As-tu un probl\u00e8me avec un camarade?",
        "As-tu un probl\u00e8me avec un de tes camarades?",
        "As-tu un probl\u00e8me avec un ami?",
        "As-tu un probl\u00e8me avec un de tes amis?",
        "As-tu un probl\u00e8me avec une amie?",
        "As-tu un probl\u00e8me avec une de tes amies?",
        "As-tu un probl\u00e8me avec un copain?",
        "As-tu un probl\u00e8me avec un de tes copains?",
        "As-tu un probl\u00e8me avec une copine?",
        "As-tu un probl\u00e8me avec une de tes copines?",
        "Tu as un probl\u00e8me avec un camarade?",
        "Tu as un probl\u00e8me avec un de tes camarades?",
        "Tu as un probl\u00e8me avec un ami?",
        "Tu as un probl\u00e8me avec un de tes amis?",
        "Tu as un probl\u00e8me avec une amie?",
        "Tu as un probl\u00e8me avec une de tes amies?",
        "Tu as un probl\u00e8me avec un copain?",
        "Tu as un probl\u00e8me avec un de tes copains?",
        "Tu as un probl\u00e8me avec une copine?",
        "Tu as un probl\u00e8me avec une de tes copines?",
        "T'as un probl\u00e8me avec un camarade?",
        "T'as un probl\u00e8me avec un de tes camarades?",
        "T'as un probl\u00e8me avec un ami?",
        "T'as un probl\u00e8me avec un de tes amis?",
        "T'as un probl\u00e8me avec une amie?",
        "T'as un probl\u00e8me avec une de tes amies?",
        "T'as un probl\u00e8me avec un copain?",
        "T'as un probl\u00e8me avec un de tes copains?",
        "T'as un probl\u00e8me avec une copine?",
        "T'as un probl\u00e8me avec une de tes copines?",
        "Est-ce que tu as un probl\u00e8me avec un camarade?",
        "Est-ce que tu as un probl\u00e8me avec un de tes camarades?",
        "Est-ce que tu as un probl\u00e8me avec un ami?",
        "Est-ce que tu as un probl\u00e8me avec un de tes amis?",
        "Est-ce que tu as un probl\u00e8me avec une amie?",
        "Est-ce que tu as un probl\u00e8me avec une de tes amies?",
        "Est-ce que tu as un probl\u00e8me avec un copain?",
        "Est-ce que tu as un probl\u00e8me avec un de tes copains?",
        "Est-ce que tu as un probl\u00e8me avec une copine?",
        "Est-ce que tu as un probl\u00e8me avec une de tes copines?",
        "Avez-vous un probl\u00e8me avec un camarade?",
        "Avez-vous un probl\u00e8me avec un de tes camarades?",
        "Avez-vous un probl\u00e8me avec un ami?",
        "Avez-vous un probl\u00e8me avec un de tes amis?",
        "Avez-vous un probl\u00e8me avec une amie?",
        "Avez-vous un probl\u00e8me avec une de tes amies?",
        "Avez-vous un probl\u00e8me avec un copain?",
        "Avez-vous un probl\u00e8me avec un de tes copains?",
        "Avez-vous un probl\u00e8me avec une copine?",
        "Avez-vous un probl\u00e8me avec une de tes copines?",
        "Vous avez un probl\u00e8me avec un camarade?",
        "Vous avez un probl\u00e8me avec un de tes camarades?",
        "Vous avez un probl\u00e8me avec un ami?",
        "Vous avez un probl\u00e8me avec un de tes amis?",
        "Vous avez un probl\u00e8me avec une amie?",
        "Vous avez un probl\u00e8me avec une de tes amies?",
        "Vous avez un probl\u00e8me avec un copain?",
        "Vous avez un probl\u00e8me avec un de tes copains?",
        "Vous avez un probl\u00e8me avec une copine?",
        "Vous avez un probl\u00e8me avec une de tes copines?",
        "Est-ce que vous avez un probl\u00e8me avec un camarade?",
        "Est-ce que vous avez un probl\u00e8me avec un de tes camarades?",
        "Est-ce que vous avez un probl\u00e8me avec un ami?",
        "Est-ce que vous avez un probl\u00e8me avec un de tes amis?",
        "Est-ce que vous avez un probl\u00e8me avec une amie?",
        "Est-ce que vous avez un probl\u00e8me avec une de tes amies?",
        "Est-ce que vous avez un probl\u00e8me avec un copain?",
        "Est-ce que vous avez un probl\u00e8me avec un de tes copains?",
        "Est-ce que vous avez un probl\u00e8me avec une copine?",
        "Est-ce que vous avez un probl\u00e8me avec une de tes copines?"
      ]
    }
  ]
}
